{
	"professional_experiences": [
		{
			"technos": [
				{
					"name": "NodeJS",
					"img": "http://dius.wordpress.dius.com.au/wp-content/uploads/sites/2/2015/06/NodeJS-Small-Blog-Feature-Image-.jpg"
				},
				{
					"name": "AngularJS",
					"img": "https://d1xwtr0qwr70yv.cloudfront.net/assets/tech/angularjs-d9843478308663db6920611ae2353d81.svg"
				},
				{
					"name": "MongoDB",
					"img": "http://blog.fabianpiau.com/wp-content/uploads/2013/01/00048.png"
				},
				{
					"name": "Elastic",
					"img": "https://www.elastic.co/static/img/elastic-logo-200.png"
				}
			]
		},
		{
			"technos": [
				{
					"name": "PHP",
					"img": "http://seeklogo.com/images/E/ElePHPant_-_Mascot_PHP-logo-4C78D1AC4E-seeklogo.com.gif"
				},
				{
					"name": "JQuery",
					"img": "http://www.cheesetoast.co.uk/cheesepress/wp-content/uploads/2010/07/jquery-logo.jpg"
				}
			]
		}
	],
	"projects": [
		{
			"cover": "/images/hapi/alarms.png",
			"technos": ["ReactJS", "React Native", "NodeJs", "Socket.io", "MongoDB", "Python", "Raspberry pi"],
			"links": [
				{
					"name": "server",
					"url": "to do"
				}
			],
			"images": [
				"/images/hapi/new-alarm.PNG",
				"/images/hapi/player.PNG"
			]
		},
		{
			"technos": ["NodeJs", "Socket.io", "MongoDB", "Java", "Arduino"],
			"cover": "/images/arduino-light/main screen.png",
			"links": [
				{
					"name": "Server",
					"url": "https://github.com/youennPennarun/Arduino_light_switcher_server"
				},
				{
					"name": "Driver",
					"url": "https://github.com/youennPennarun/Arduino_light_switcher_Driver"
				},
				{
					"name": "Control panel",
					"url": "https://github.com/youennPennarun/Arduino_light_switcher_Admin_app"
				}
			],
			"images": [
				"/images/arduino-light/HA_Splash.jpg",
				"/images/arduino-light/light screen.PNG",
				"/images/arduino-light/main screen.png",
				"/images/arduino-light/weather.PNG"
			]
		}
	]
}